laika/__init__.py
laika/reports.py
laika/examples/adwords_config.json
laika/examples/aws_config.json
laika/examples/config.json
laika/examples/custom_module.py
laika/examples/drive_config.json
laika/examples/email_config.json
laika/examples/fb_config.json
laika/examples/module_config.json
laika/tests/__init__.py
laika/tests/test_formatter.py
laika/tests/test_laika.py
laika_lib-1.4.0.data/scripts/laika.py
laika_lib-1.4.0.dist-info/LICENSE
laika_lib-1.4.0.dist-info/METADATA
laika_lib-1.4.0.dist-info/WHEEL
laika_lib-1.4.0.dist-info/top_level.txt
laika_lib-1.4.0.dist-info/RECORD
