Metadata-Version: 2.1
Name: laika-lib
Version: 1.4.0
Summary: A simple business reporting library
Home-page: https://github.com/trocafone/laika
Author: Seva Gavrilov
Author-email: gavrilovseva@gmail.com
Maintainer: Trocafone Data Science Team
Maintainer-email: ds@trocafone.com
License: MIT
Keywords: report reporting etl sql s3 drive ftp adwords
Platform: UNKNOWN
Classifier: Development Status :: 3 - Alpha
Classifier: Environment :: Console
Classifier: Intended Audience :: Developers
Classifier: Intended Audience :: System Administrators
Classifier: License :: OSI Approved :: MIT License
Classifier: Programming Language :: Python
Classifier: Programming Language :: Python :: 2
Classifier: Programming Language :: Python :: 2.7
Classifier: Programming Language :: Python :: 3
Classifier: Programming Language :: Python :: 3.5
Classifier: Programming Language :: Python :: 3.6
License-File: LICENSE
Requires-Dist: click (==6.2)
Requires-Dist: pandas (==0.23.4)
Requires-Dist: requests (>=2.21.0)
Requires-Dist: six (>=1.11.0)
Provides-Extra: adwords
Requires-Dist: googleads (==19.0.0) ; extra == 'adwords'
Provides-Extra: all_reports
Requires-Dist: xlrd (==1.1.0) ; extra == 'all_reports'
Requires-Dist: XlsxWriter (==0.8.4) ; extra == 'all_reports'
Requires-Dist: SQLAlchemy (==1.2.17) ; extra == 'all_reports'
Requires-Dist: psycopg2 (==2.8.5) ; extra == 'all_reports'
Requires-Dist: PyHive[presto] (==0.6.1) ; extra == 'all_reports'
Requires-Dist: PyDrive (==1.3.1) ; extra == 'all_reports'
Requires-Dist: httplib2 (>=0.17.0) ; extra == 'all_reports'
Requires-Dist: googleads (==19.0.0) ; extra == 'all_reports'
Requires-Dist: boto3 (==1.14.3) ; extra == 'all_reports'
Requires-Dist: paramiko (==2.6.0) ; extra == 'all_reports'
Requires-Dist: bingads (==13.0.10) ; extra == 'all_reports'
Provides-Extra: bingads
Requires-Dist: bingads (==13.0.10) ; extra == 'bingads'
Provides-Extra: docs
Requires-Dist: Sphinx (>=1.7.1) ; extra == 'docs'
Requires-Dist: sphinx-rtd-theme (>=0.2.4) ; extra == 'docs'
Provides-Extra: drive
Requires-Dist: PyDrive (==1.3.1) ; extra == 'drive'
Requires-Dist: httplib2 (>=0.17.0) ; extra == 'drive'
Provides-Extra: excel
Requires-Dist: xlrd (==1.1.0) ; extra == 'excel'
Requires-Dist: XlsxWriter (==0.8.4) ; extra == 'excel'
Provides-Extra: postgres
Requires-Dist: SQLAlchemy (==1.2.17) ; extra == 'postgres'
Requires-Dist: psycopg2 (==2.8.5) ; extra == 'postgres'
Provides-Extra: presto
Requires-Dist: SQLAlchemy (==1.2.17) ; extra == 'presto'
Requires-Dist: PyHive[presto] (==0.6.1) ; extra == 'presto'
Provides-Extra: s3
Requires-Dist: boto3 (==1.14.3) ; extra == 's3'
Provides-Extra: sftp
Requires-Dist: paramiko (==2.6.0) ; extra == 'sftp'
Provides-Extra: sql
Requires-Dist: SQLAlchemy (==1.2.17) ; extra == 'sql'
Provides-Extra: test
Requires-Dist: mock (==1.3.0) ; extra == 'test'
